pycomlink/__init__.py
pycomlink/io/__init__.py
pycomlink/io/cmlh5_to_xarray.py
pycomlink/io/examples.py
pycomlink/io/example_data/75_cmls.h5
pycomlink/io/example_data/75_cmls_min_max.h5
pycomlink/io/example_data/example_areal_reference_data.nc
pycomlink/io/example_data/example_cml_data.nc
pycomlink/io/example_data/example_path_averaged_reference_data.nc
pycomlink/io/example_data/gap0_gap4_2012.csv
pycomlink/io/example_data/one_cml.h5
pycomlink/processing/__init__.py
pycomlink/processing/baseline.py
pycomlink/processing/blackout_gap_detection.py
pycomlink/processing/k_R_relation.py
pycomlink/processing/min_max.py
pycomlink/processing/nearby_rain_retrival.py
pycomlink/processing/wet_antenna.py
pycomlink/processing/xarray_wrapper.py
pycomlink/processing/anomaly_detection/__init__.py
pycomlink/processing/pytorch_utils/__init__.py
pycomlink/processing/pytorch_utils/inference_utils.py
pycomlink/processing/pytorch_utils/pytorch_utils.py
pycomlink/processing/pytorch_utils/run_inference.py
pycomlink/processing/tensorflow_utils/__init__.py
pycomlink/processing/tensorflow_utils/inference_utils.py
pycomlink/processing/tensorflow_utils/lazy_tf.py
pycomlink/processing/tensorflow_utils/run_inference.py
pycomlink/processing/wet_dry/__init__.py
pycomlink/processing/wet_dry/mlp.py
pycomlink/processing/wet_dry/nearby_wetdry.py
pycomlink/processing/wet_dry/stft.py
pycomlink/processing/wet_dry/mlp_model_files/model_rad.pkl
pycomlink/processing/wet_dry/mlp_model_files/model_rad_online.pkl
pycomlink/processing/wet_dry/mlp_model_files/model_rg.pkl
pycomlink/processing/wet_dry/mlp_model_files/model_rg_online.pkl
pycomlink/spatial/__init__.py
pycomlink/spatial/coverage.py
pycomlink/spatial/helper.py
pycomlink/spatial/idw.py
pycomlink/spatial/interpolator.py
pycomlink/tests/__init__.py
pycomlink/tests/test_blackout_gap_detection.py
pycomlink/tests/test_cmlh5_to_xarray.py
pycomlink/tests/test_idw.py
pycomlink/tests/test_interpolator.py
pycomlink/tests/test_k_R_relation.py
pycomlink-0.6.0.dist-info/licenses/LICENSE
pycomlink-0.6.0.dist-info/METADATA
pycomlink-0.6.0.dist-info/WHEEL
pycomlink-0.6.0.dist-info/pbr.json
pycomlink-0.6.0.dist-info/top_level.txt
pycomlink-0.6.0.dist-info/RECORD
