Metadata-Version: 2.4
Name: pycomlink
Version: 0.6.0
Summary: Python tools for CML (commercial microwave link) data processing
Home-page: https://github.com/pycomlink/pycomlink
Download-URL: https://github.com/pycomlink/pycomlink/archive/0.6.0.tar.gz
Author: Christian Chwala
Author-email: christian.chwala@kit.edu
License: BSD
Keywords: microwave links precipitation radar cml
Classifier: Development Status :: 3 - Alpha
Classifier: Topic :: Scientific/Engineering :: Atmospheric Science
Classifier: License :: OSI Approved :: BSD License
Classifier: Programming Language :: Python :: 3.10
Classifier: Programming Language :: Python :: 3.11
Classifier: Programming Language :: Python :: 3.12
Classifier: Programming Language :: Python :: 3.13
License-File: LICENSE
Requires-Dist: numpy
Requires-Dist: scipy
Requires-Dist: pandas
Requires-Dist: matplotlib
Requires-Dist: numba
Requires-Dist: h5py<=3.14
Requires-Dist: xarray
Requires-Dist: sparse
Requires-Dist: netcdf4
Requires-Dist: shapely
Requires-Dist: pyproj
Requires-Dist: tqdm
Requires-Dist: pykrige
Requires-Dist: scikit-learn
Requires-Dist: future
Requires-Dist: bottleneck
Requires-Dist: poligrain
Dynamic: author
Dynamic: author-email
Dynamic: classifier
Dynamic: description
Dynamic: download-url
Dynamic: home-page
Dynamic: keywords
Dynamic: license
Dynamic: license-file
Dynamic: requires-dist
Dynamic: summary
